[{"kind":"component","drawable":0,"texture":0,"id":1},{"kind":"component","drawable":41,"texture":0,"id":11},{"kind":"component","drawable":15,"texture":0,"id":8},{"kind":"component","drawable":1,"texture":0,"id":3},{"kind":"component","drawable":1,"texture":0,"id":4},{"kind":"component","drawable":1,"texture":0,"id":6},{"kind":"component","drawable":0,"texture":0,"id":5},{"kind":"component","drawable":0,"texture":0,"id":7},{"kind":"component","drawable":0,"texture":0,"id":9},{"kind":"component","drawable":0,"texture":0,"id":10},{"kind":"prop","drawable":-1,"texture":-1,"id":0},{"kind":"prop","drawable":11,"texture":0,"id":1},{"kind":"prop","drawable":-1,"texture":-1,"id":2},{"kind":"prop","drawable":-1,"texture":-1,"id":6},{"kind":"prop","drawable":-1,"texture":-1,"id":7}]